nomenklatura.py
setup.py
pynomenklatura.egg-info/PKG-INFO
pynomenklatura.egg-info/SOURCES.txt
pynomenklatura.egg-info/dependency_links.txt
pynomenklatura.egg-info/entry_points.txt
pynomenklatura.egg-info/not-zip-safe
pynomenklatura.egg-info/requires.txt
pynomenklatura.egg-info/top_level.txt