Metadata-Version: 1.0
Name: pynomenklatura
Version: 0.3
Summary: Client library for nomenklatura, make record linkages on the web.
Home-page: http://github.com/okfn/nomenklatura-client
Author: Open Knowledge Foundation
Author-email: info@okfn.org
License: AGPLv3
Keywords: data mapping identity linkage record
Platform: UNKNOWN
